{
	"configurations" : 
	[
		{
			"directories" : 
			[
				{
					"build" : ".",
					"jsonFile" : "directory-.-Debug-f5ebdc15457944623624.json",
					"minimumCMakeVersion" : 
					{
						"string" : "3.28"
					},
					"projectIndex" : 0,
					"source" : ".",
					"targetIndexes" : 
					[
						0
					]
				}
			],
			"name" : "Debug",
			"projects" : 
			[
				{
					"directoryIndexes" : 
					[
						0
					],
					"name" : "Concurrent_Programming",
					"targetIndexes" : 
					[
						0
					]
				}
			],
			"targets" : 
			[
				{
					"directoryIndex" : 0,
					"id" : "Concurrent_Programming::@6890427a1f51a3e7e1df",
					"jsonFile" : "target-Concurrent_Programming-Debug-a1acd374bf74b2cc8bc1.json",
					"name" : "Concurrent_Programming",
					"projectIndex" : 0
				}
			]
		}
	],
	"kind" : "codemodel",
	"paths" : 
	{
		"build" : "/home/oem/Projects/Operating systems/Concurrent_Programming/cmake-build-debug",
		"source" : "/home/oem/Projects/Operating systems/Concurrent_Programming"
	},
	"version" : 
	{
		"major" : 2,
		"minor" : 6
	}
}
